gda_importer/__init__.py
gda_importer/__main__.py
gda_importer/models.py
gda_importer/ppinfo.py
gda_importer/pull_private_deps.py
gda_importer/uv_check_ppd.py
gda_importer-1.9.6.dist-info/licenses/AUTHORS.md
gda_importer-1.9.6.dist-info/licenses/LICENSE
gda_importer-1.9.6.dist-info/METADATA
gda_importer-1.9.6.dist-info/WHEEL
gda_importer-1.9.6.dist-info/entry_points.txt
gda_importer-1.9.6.dist-info/top_level.txt
gda_importer-1.9.6.dist-info/RECORD
