Metadata-Version: 2.4
Name: gda-importer
Version: 1.9.6
Summary: GDA Importer provides simple command-line utilities that aide the installation of Python packages.
Author-email: "Abraham D. Smith (Geometric Data Analytics, Inc)" <abraham.smith@geomdata.com>
License: AGPLv3
Project-URL: Documentation, https://geomdata.pages.geomdata.com/gda-importer
Project-URL: Source, https://gitlab.geomdata.com/geomdata/gda-importer
Requires-Python: <3.15,>=3.10
License-File: LICENSE
License-File: AUTHORS.md
Requires-Dist: keyring
Requires-Dist: packaging
Requires-Dist: pydantic<3,>=1
Requires-Dist: requests
Requires-Dist: toml
Provides-Extra: ruff
Requires-Dist: ruff<0.6,>=0.5; extra == "ruff"
Provides-Extra: notebooks
Provides-Extra: testing
Requires-Dist: pytest; extra == "testing"
Requires-Dist: pytest-cov; extra == "testing"
Requires-Dist: pytest-html; extra == "testing"
Requires-Dist: pytest-timeout; extra == "testing"
Requires-Dist: pytest-shell-utilities; extra == "testing"
Requires-Dist: pytest-xdist; extra == "testing"
Provides-Extra: docs
Requires-Dist: griffe<1.0; extra == "docs"
Requires-Dist: quarto; extra == "docs"
Requires-Dist: quartodoc; extra == "docs"
Requires-Dist: toml; extra == "docs"
Dynamic: license-file
